LICENSE.txt
setup.py
MLIB/__init__.py
simcalc.egg-info/PKG-INFO
simcalc.egg-info/SOURCES.txt
simcalc.egg-info/dependency_links.txt
simcalc.egg-info/top_level.txt