Metadata-Version: 2.1
Name: simcalc
Version: 0.1
Summary: Simple library in python for test
Author: Ali-Rida
Classifier: Programming Language :: Python :: 3
Classifier: Operating System :: OS Independent
Classifier: License :: OSI Approved :: MIT License 
License-File: LICENSE.txt
